README.md
setup.cfg
setup.py
stingray_cli/__init__.py
stingray_cli/run_stingray_scan.py
stingray_cli.egg-info/PKG-INFO
stingray_cli.egg-info/SOURCES.txt
stingray_cli.egg-info/dependency_links.txt
stingray_cli.egg-info/entry_points.txt
stingray_cli.egg-info/requires.txt
stingray_cli.egg-info/top_level.txt
stingray_cli/distribution_systems/__init__.py
stingray_cli/distribution_systems/app_center.py
stingray_cli/distribution_systems/base.py
stingray_cli/distribution_systems/hockey_app.py
stingray_cli/helpers/__init__.py
stingray_cli/helpers/const.py
stingray_cli/helpers/helpers.py
stingray_cli/helpers/logging.py