Metadata-Version: 2.1
Name: stingray-cli
Version: 2.1.1
Summary: Stingray cli package
Home-page: https://github.com/Swordfish-Security/stingray_cli
Author: Stingray Technologies LLC
Author-email: stingray@appsec.global
License: UNKNOWN
Platform: UNKNOWN
Classifier: Programming Language :: Python :: 3
Classifier: License :: OSI Approved :: MIT License
Classifier: Operating System :: Unix
